citation/__init__.py
citation/citation_style.py
citation/cli.py
citation/file_converter.py
citation/llm.py
citation/main.py
citation/main.py.backup2
citation/main.py.backup_20250802_130432
citation/model.py
citation/ocr_lang_detect.py
citation/ocr_text_clean_before_llm.py
citation/ocr_text_clean_before_llm.py.backup_20250802_131627
citation/page_extractor.py
citation/search.py
citation/type_judge.py
citation/utils.py
citation/vertical_handler.py
citation/vertical_handler.py.backup
citation/vertical_llm.py
citation/styles/chicago-author-date.csl
citation/tests/__init__.py
citation/tests/test_citation.py
citation/tests/test_llm_extraction.py
cite_extractor-0.10.8.dist-info/METADATA
cite_extractor-0.10.8.dist-info/WHEEL
cite_extractor-0.10.8.dist-info/entry_points.txt
cite_extractor-0.10.8.dist-info/RECORD
