Metadata-Version: 2.3
Name: cite-extractor
Version: 0.10.8
Summary: Extracts citations from PDF, URLs and local media files in CSL-JSON. 
Author-email: ajia <yyjfwoaini@gmail.com>
License: MIT
Requires-Python: >=3.12
Requires-Dist: citeproc-py>=0.7.0
Requires-Dist: crawl4ai>=0.7.0
Requires-Dist: dspy-ai>=2.6.27
Requires-Dist: fasttext>=0.9.2
Requires-Dist: lxml>=4.9.0
Requires-Dist: ocrmypdf>=16.10.4
Requires-Dist: paddleocr>=3.1.0
Requires-Dist: paddlepaddle>=3.1.0
Requires-Dist: pymediainfo>=7.0.1
Requires-Dist: pymupdf[mupdf-third]>=1.26.3
Requires-Dist: pypinyin>=0.51.0
Requires-Dist: python-dateutil>=2.8.0
Requires-Dist: requests>=2.31.0
Requires-Dist: setuptools>=80.9.0
Requires-Dist: trafilatura>=1.6.0
Requires-Dist: urllib3>=2.0.0
Requires-Dist: yt-dlp>=2025.7.21
